loglu/__init__.py
loglu/loglu.py
loglu-1.1.5.dist-info/METADATA
loglu-1.1.5.dist-info/WHEEL
loglu-1.1.5.dist-info/top_level.txt
loglu-1.1.5.dist-info/RECORD
