Metadata-Version: 2.1
Name: loglu
Version: 1.1.5
Summary: The Logarithmic Linear Unit (LogLU) is a novel activation function designed for deep neural networks, improving convergence speed, stability, and overall model performance
Home-page: https://github.com/Rishichaitanya-Nalluri/LogLU
Author: Rishi Chaitanya Sri Prasad Nalluri
Author-email: rishichaitanya888@gmail.com
License: Apache-2.0
Classifier: Programming Language :: Python :: 3
Classifier: License :: OSI Approved :: Apache Software License
Classifier: Operating System :: OS Independent
Classifier: Intended Audience :: Developers
Classifier: Intended Audience :: Science/Research
Classifier: Topic :: Scientific/Engineering :: Artificial Intelligence
Requires-Python: >=3.6
Requires-Dist: tensorflow>=2.10.0
Requires-Dist: keras>=2.10.0
